odoo/addons/l10n_it_fatturapa_out_di/README.rst
odoo/addons/l10n_it_fatturapa_out_di/__init__.py
odoo/addons/l10n_it_fatturapa_out_di/__manifest__.py
odoo/addons/l10n_it_fatturapa_out_di/data/invoice_it_template.xml
odoo/addons/l10n_it_fatturapa_out_di/i18n/it.po
odoo/addons/l10n_it_fatturapa_out_di/i18n/l10n_it_fatturapa_out_di.pot
odoo/addons/l10n_it_fatturapa_out_di/i18n/l10n_it_fatturapa_out_sp.pot
odoo/addons/l10n_it_fatturapa_out_di/readme/CONTRIBUTORS.md
odoo/addons/l10n_it_fatturapa_out_di/readme/DESCRIPTION.md
odoo/addons/l10n_it_fatturapa_out_di/static/description/icon.png
odoo/addons/l10n_it_fatturapa_out_di/static/description/index.html
odoo/addons/l10n_it_fatturapa_out_di/tests/__init__.py
odoo/addons/l10n_it_fatturapa_out_di/tests/fatturapa_common.py
odoo/addons/l10n_it_fatturapa_out_di/tests/test_fatturapa_xml_validation.py
odoo/addons/l10n_it_fatturapa_out_di/tests/data/IT06363391001_00001.xml
odoo/addons/l10n_it_fatturapa_out_di/tests/data/IT06363391001_00002.xml
odoo/addons/l10n_it_fatturapa_out_di/tests/data/IT06363391001_00003.xml
odoo_addon_l10n_it_fatturapa_out_di-16.0.1.0.2.dist-info/METADATA
odoo_addon_l10n_it_fatturapa_out_di-16.0.1.0.2.dist-info/WHEEL
odoo_addon_l10n_it_fatturapa_out_di-16.0.1.0.2.dist-info/top_level.txt
odoo_addon_l10n_it_fatturapa_out_di-16.0.1.0.2.dist-info/RECORD
